b_cfn_s3_large_deployment/__init__.py
b_cfn_s3_large_deployment/deployment_props.py
b_cfn_s3_large_deployment/deployment_source.py
b_cfn_s3_large_deployment/efs_props.py
b_cfn_s3_large_deployment/function.py
b_cfn_s3_large_deployment/resource.py
b_cfn_s3_large_deployment/source/__init__.py
b_cfn_s3_large_deployment/source/main/__init__.py
b_cfn_s3_large_deployment/source/main/action.py
b_cfn_s3_large_deployment/source/main/cfnresponse.py
b_cfn_s3_large_deployment/source/main/index.py
b_cfn_s3_large_deployment/source/main/large_deployment.py
b_cfn_s3_large_deployment-1.2.0.dist-info/LICENSE
b_cfn_s3_large_deployment-1.2.0.dist-info/METADATA
b_cfn_s3_large_deployment-1.2.0.dist-info/WHEEL
b_cfn_s3_large_deployment-1.2.0.dist-info/top_level.txt
b_cfn_s3_large_deployment-1.2.0.dist-info/RECORD
