Metadata-Version: 2.1
Name: b-cfn-s3-large-deployment
Version: 1.2.0
Summary: AWS CDK custom resource that handles large files deployment to S3 bucket.
Home-page: https://github.com/Biomapas/B.CfnS3LargeDeployment
Author: Matas Gumbinas
Author-email: matas.gumbinas@biomapas.com
License: Apache License 2.0
Keywords: AWS CDK CustomResource S3 Deployment
Platform: UNKNOWN
Classifier: Programming Language :: Python :: 3
Classifier: Operating System :: OS Independent
Requires-Dist: aws-cdk.aws-ec2 (<2.0.0,>=1.152.0)
Requires-Dist: aws-cdk.aws-iam (<2.0.0,>=1.152.0)
Requires-Dist: aws-cdk.aws-lambda (<2.0.0,>=1.152.0)
Requires-Dist: aws-cdk.aws-s3 (<2.0.0,>=1.152.0)
Requires-Dist: aws-cdk.aws-s3-assets (<2.0.0,>=1.152.0)
Requires-Dist: aws-cdk.core (<2.0.0,>=1.152.0)
Requires-Dist: aws-cdk.lambda-layer-awscli (<2.0.0,>=1.152.0)
Requires-Dist: b-aws-cdk-parallel (<3.0.0,>=2.2.0)
Requires-Dist: b-aws-cf (<1.0.0,>=0.2.1)
Requires-Dist: b-aws-testing-framework (<2.0.0,>=0.6.0)
Requires-Dist: boto3 (<2.0.0,>=1.18.32)
Requires-Dist: urllib3 (<2.0.0,>=1.26.6)
